cli/__init__.py
cli/const.py
cli/demo.py
cli/utils.py
cli/video_specs.py
helpers/__init__.py
helpers/converter.py
helpers/from_html.py
helpers/from_json.py
helpers/from_text_blocks.py
helpers/from_xml.py
helpers/to_html.py
helpers/to_text_blocks.py
helpers/to_xml.py
video_specs-0.1.51.dist-info/licenses/LICENSE
video_specs-0.1.51.dist-info/METADATA
video_specs-0.1.51.dist-info/WHEEL
video_specs-0.1.51.dist-info/entry_points.txt
video_specs-0.1.51.dist-info/top_level.txt
video_specs-0.1.51.dist-info/RECORD
