Metadata-Version: 2.4
Name: video-specs
Version: 0.1.51
Summary: Add your description here
Requires-Python: >=3.11
License-File: LICENSE
Requires-Dist: click>=8.3.1
Requires-Dist: markdown-it-py>=3.0.0
Requires-Dist: mdurl>=0.1.2
Requires-Dist: pygments>=2.19.2
Requires-Dist: rich>=14.2.0
Requires-Dist: rich-click>=1.9.4
Dynamic: license-file
